{"Nodes":[],"ExecutionTime":"2024-04-15T12:13:17.8080325Z","GenerationTime":"0001-01-01T00:00:00","PluginUserSpecFlowId":"919ce326-e95a-4a3d-80b2-4c2a47e4a448","CLIUserSpecFlowId":null,"ExecutionResults":[{"ContextType":"Scenario","FeatureFolderPath":"Features","FeatureTitle":"Feature1","ScenarioTitle":"User able to login in Mars portal with invalid Cerdentials","ScenarioArguments":["'dhivya@gamkil.com'","'dhivya1'"],"Status":"OK","StepResults":[{"Duration":"00:00:08.9129646","Status":"OK","Error":null,"Outputs":null}],"Outputs":null}],"StepReports":null}